excel_orm/__init__.py
excel_orm/base.py
excel_orm/column.py
excel_orm/orm.py
excel_orm-0.1.4.dist-info/METADATA
excel_orm-0.1.4.dist-info/WHEEL
excel_orm-0.1.4.dist-info/RECORD
