Metadata-Version: 2.4
Name: excel-orm
Version: 0.1.4
Summary: A lightweight Excel ORM for generating templates and parsing typed row models.
Project-URL: Homepage, https://github.com/acdelrusso/excel-orm
Project-URL: Repository, https://github.com/acdelrusso/excel-orm
Project-URL: Issues, https://github.com/acdelrusso/excel-orm/issues
Author: Anthony Del Russo
License: MIT
Keywords: etl,excel,openpyxl,orm
Classifier: Development Status :: 3 - Alpha
Classifier: License :: OSI Approved :: MIT License
Classifier: Operating System :: OS Independent
Classifier: Programming Language :: Python :: 3
Classifier: Programming Language :: Python :: 3.11
Classifier: Programming Language :: Python :: 3.12
Requires-Python: >=3.13
Requires-Dist: openpyxl>=3.1.5
